stringconsts/__init__.py
stringconsts/core.py
stringconsts/py.typed
stringconsts-0.1.0.dist-info/licenses/LICENSE
stringconsts-0.1.0.dist-info/METADATA
stringconsts-0.1.0.dist-info/WHEEL
stringconsts-0.1.0.dist-info/top_level.txt
stringconsts-0.1.0.dist-info/RECORD
