Metadata-Version: 2.4
Name: stringconsts
Version: 0.1.0
Summary: Automatic generation of string constants from attribute names with optional handler
Author-email: Rus Sh <break1@yandex.ru>
License: MIT License
Classifier: Programming Language :: Python :: 3
Classifier: License :: OSI Approved :: MIT License
Classifier: Operating System :: OS Independent
Requires-Python: >=3.9
License-File: LICENSE
Provides-Extra: dev
Requires-Dist: pytest>=7.0; extra == "dev"
Dynamic: license-file
